{
  "case_01": {
    "params": {
      "Z": 128,
      "H": 8,
      "N_CTX": 1024,
      "HEAD_DIM": 128,
      "causal": true,
      "dtype": "torch.float16"
    },
    "best": {
      "BM": 128,
      "BN": 64,
      "avg_ms": 8.9017
    },
    "top3": [
      {
        "BM": 128,
        "BN": 64,
        "avg_ms": 8.9017
      },
      {
        "BM": 64,
        "BN": 256,
        "avg_ms": 11.3879
      },
      {
        "BM": 32,
        "BN": 256,
        "avg_ms": 28.8426
      }
    ],
    "all_tested": [
      {
        "BM": 128,
        "BN": 64,
        "avg_ms": 8.9017
      },
      {
        "BM": 64,
        "BN": 256,
        "avg_ms": 11.3879
      },
      {
        "BM": 32,
        "BN": 256,
        "avg_ms": 28.8426
      },
      {
        "BM": 64,
        "BN": 128,
        "avg_ms": 29.5267
      },
      {
        "BM": 128,
        "BN": 32,
        "avg_ms": 37.2448
      },
      {
        "BM": 64,
        "BN": 64,
        "avg_ms": 43.1135
      },
      {
        "BM": 32,
        "BN": 64,
        "avg_ms": 51.5978
      },
      {
        "BM": 64,
        "BN": 32,
        "avg_ms": 58.4425
      },
      {
        "BM": 32,
        "BN": 128,
        "avg_ms": 78.5552
      },
      {
        "BM": 32,
        "BN": 32,
        "avg_ms": 93.9133
      }
    ],
    "failed_count": 6
  },
  "case_02": {
    "params": {
      "Z": 128,
      "H": 8,
      "N_CTX": 1024,
      "HEAD_DIM": 256,
      "causal": true,
      "dtype": "torch.float16"
    },
    "best": {
      "BM": 64,
      "BN": 256,
      "avg_ms": 12.783
    },
    "top3": [
      {
        "BM": 64,
        "BN": 256,
        "avg_ms": 12.783
      },
      {
        "BM": 64,
        "BN": 128,
        "avg_ms": 16.4445
      },
      {
        "BM": 32,
        "BN": 256,
        "avg_ms": 21.7843
      }
    ],
    "all_tested": [
      {
        "BM": 64,
        "BN": 256,
        "avg_ms": 12.783
      },
      {
        "BM": 64,
        "BN": 128,
        "avg_ms": 16.4445
      },
      {
        "BM": 32,
        "BN": 256,
        "avg_ms": 21.7843
      },
      {
        "BM": 64,
        "BN": 64,
        "avg_ms": 26.1393
      },
      {
        "BM": 64,
        "BN": 32,
        "avg_ms": 27.9577
      },
      {
        "BM": 32,
        "BN": 128,
        "avg_ms": 30.7007
      },
      {
        "BM": 32,
        "BN": 64,
        "avg_ms": 51.5056
      },
      {
        "BM": 32,
        "BN": 32,
        "avg_ms": 94.3573
      }
    ],
    "failed_count": 4
  },
  "case_03": {
    "params": {
      "Z": 128,
      "H": 8,
      "N_CTX": 2048,
      "HEAD_DIM": 128,
      "causal": true,
      "dtype": "torch.float16"
    },
    "best": {
      "BM": 128,
      "BN": 64,
      "avg_ms": 28.6128
    },
    "top3": [
      {
        "BM": 128,
        "BN": 64,
        "avg_ms": 28.6128
      },
      {
        "BM": 64,
        "BN": 256,
        "avg_ms": 32.6724
      },
      {
        "BM": 64,
        "BN": 128,
        "avg_ms": 53.1524
      }
    ],
    "all_tested": [
      {
        "BM": 128,
        "BN": 64,
        "avg_ms": 28.6128
      },
      {
        "BM": 64,
        "BN": 256,
        "avg_ms": 32.6724
      },
      {
        "BM": 64,
        "BN": 128,
        "avg_ms": 53.1524
      },
      {
        "BM": 128,
        "BN": 32,
        "avg_ms": 69.9378
      },
      {
        "BM": 32,
        "BN": 256,
        "avg_ms": 97.1516
      },
      {
        "BM": 64,
        "BN": 64,
        "avg_ms": 187.9154
      },
      {
        "BM": 32,
        "BN": 128,
        "avg_ms": 232.4076
      },
      {
        "BM": 32,
        "BN": 64,
        "avg_ms": 317.0203
      },
      {
        "BM": 64,
        "BN": 32,
        "avg_ms": 353.803
      },
      {
        "BM": 32,
        "BN": 32,
        "avg_ms": 367.9934
      }
    ],
    "failed_count": 6
  },
  "case_04": {
    "params": {
      "Z": 128,
      "H": 8,
      "N_CTX": 2048,
      "HEAD_DIM": 256,
      "causal": true,
      "dtype": "torch.float16"
    },
    "best": {
      "BM": 64,
      "BN": 256,
      "avg_ms": 36.125
    },
    "top3": [
      {
        "BM": 64,
        "BN": 256,
        "avg_ms": 36.125
      },
      {
        "BM": 64,
        "BN": 128,
        "avg_ms": 55.5216
      },
      {
        "BM": 32,
        "BN": 256,
        "avg_ms": 66.8782
      }
    ],
    "all_tested": [
      {
        "BM": 64,
        "BN": 256,
        "avg_ms": 36.125
      },
      {
        "BM": 64,
        "BN": 128,
        "avg_ms": 55.5216
      },
      {
        "BM": 32,
        "BN": 256,
        "avg_ms": 66.8782
      },
      {
        "BM": 64,
        "BN": 64,
        "avg_ms": 97.3856
      },
      {
        "BM": 32,
        "BN": 128,
        "avg_ms": 146.1991
      },
      {
        "BM": 64,
        "BN": 32,
        "avg_ms": 248.7373
      },
      {
        "BM": 32,
        "BN": 64,
        "avg_ms": 453.7038
      },
      {
        "BM": 32,
        "BN": 32,
        "avg_ms": 493.3724
      }
    ],
    "failed_count": 4
  },
  "case_05": {
    "params": {
      "Z": 128,
      "H": 8,
      "N_CTX": 4096,
      "HEAD_DIM": 128,
      "causal": true,
      "dtype": "torch.float16"
    },
    "best": {
      "BM": 128,
      "BN": 32,
      "avg_ms": 134.8468
    },
    "top3": [
      {
        "BM": 128,
        "BN": 32,
        "avg_ms": 134.8468
      },
      {
        "BM": 32,
        "BN": 512,
        "avg_ms": 138.343
      },
      {
        "BM": 64,
        "BN": 128,
        "avg_ms": 196.7787
      }
    ],
    "all_tested": [
      {
        "BM": 128,
        "BN": 32,
        "avg_ms": 134.8468
      },
      {
        "BM": 32,
        "BN": 512,
        "avg_ms": 138.343
      },
      {
        "BM": 64,
        "BN": 128,
        "avg_ms": 196.7787
      },
      {
        "BM": 32,
        "BN": 256,
        "avg_ms": 215.5433
      },
      {
        "BM": 64,
        "BN": 256,
        "avg_ms": 235.2819
      },
      {
        "BM": 128,
        "BN": 64,
        "avg_ms": 405.7541
      },
      {
        "BM": 32,
        "BN": 64,
        "avg_ms": 748.0452
      },
      {
        "BM": 64,
        "BN": 64,
        "avg_ms": 1597.1795
      },
      {
        "BM": 32,
        "BN": 128,
        "avg_ms": 1859.7398
      },
      {
        "BM": 32,
        "BN": 32,
        "avg_ms": 2441.8645
      },
      {
        "BM": 64,
        "BN": 32,
        "avg_ms": 6188.5281
      }
    ],
    "failed_count": 8
  },
  "case_06": {
    "params": {
      "Z": 128,
      "H": 8,
      "N_CTX": 8192,
      "HEAD_DIM": 64,
      "causal": true,
      "dtype": "torch.float16"
    },
    "best": {
      "BM": 64,
      "BN": 256,
      "avg_ms": 402.4455
    },
    "top3": [
      {
        "BM": 64,
        "BN": 256,
        "avg_ms": 402.4455
      },
      {
        "BM": 64,
        "BN": 128,
        "avg_ms": 755.4603
      },
      {
        "BM": 32,
        "BN": 256,
        "avg_ms": 790.8198
      }
    ],
    "all_tested": [
      {
        "BM": 64,
        "BN": 256,
        "avg_ms": 402.4455
      },
      {
        "BM": 64,
        "BN": 128,
        "avg_ms": 755.4603
      },
      {
        "BM": 32,
        "BN": 256,
        "avg_ms": 790.8198
      },
      {
        "BM": 128,
        "BN": 64,
        "avg_ms": 1109.274
      },
      {
        "BM": 32,
        "BN": 512,
        "avg_ms": 1176.775
      },
      {
        "BM": 128,
        "BN": 32,
        "avg_ms": 1432.2668
      },
      {
        "BM": 32,
        "BN": 128,
        "avg_ms": 1510.8216
      },
      {
        "BM": 64,
        "BN": 32,
        "avg_ms": 1557.2453
      },
      {
        "BM": 64,
        "BN": 64,
        "avg_ms": 2434.0944
      },
      {
        "BM": 32,
        "BN": 64,
        "avg_ms": 3921.3846
      },
      {
        "BM": 32,
        "BN": 32,
        "avg_ms": 5906.7651
      }
    ],
    "failed_count": 8
  },
  "case_07": {
    "params": {
      "Z": 128,
      "H": 8,
      "N_CTX": 1024,
      "HEAD_DIM": 128,
      "causal": false,
      "dtype": "torch.float16"
    },
    "best": {
      "BM": 128,
      "BN": 256,
      "avg_ms": 19.8196
    },
    "top3": [
      {
        "BM": 128,
        "BN": 256,
        "avg_ms": 19.8196
      },
      {
        "BM": 64,
        "BN": 128,
        "avg_ms": 23.2219
      },
      {
        "BM": 128,
        "BN": 64,
        "avg_ms": 23.3648
      }
    ],
    "all_tested": [
      {
        "BM": 128,
        "BN": 256,
        "avg_ms": 19.8196
      },
      {
        "BM": 64,
        "BN": 128,
        "avg_ms": 23.2219
      },
      {
        "BM": 128,
        "BN": 64,
        "avg_ms": 23.3648
      },
      {
        "BM": 64,
        "BN": 256,
        "avg_ms": 25.2604
      },
      {
        "BM": 128,
        "BN": 128,
        "avg_ms": 29.1245
      },
      {
        "BM": 64,
        "BN": 64,
        "avg_ms": 68.3838
      },
      {
        "BM": 128,
        "BN": 32,
        "avg_ms": 68.4338
      },
      {
        "BM": 64,
        "BN": 32,
        "avg_ms": 91.5758
      },
      {
        "BM": 32,
        "BN": 256,
        "avg_ms": 214.2649
      },
      {
        "BM": 32,
        "BN": 32,
        "avg_ms": 318.0687
      },
      {
        "BM": 32,
        "BN": 64,
        "avg_ms": 321.4144
      },
      {
        "BM": 32,
        "BN": 128,
        "avg_ms": 7963.0393
      }
    ],
    "failed_count": 4
  },
  "case_08": {
    "params": {
      "Z": 128,
      "H": 8,
      "N_CTX": 1024,
      "HEAD_DIM": 256,
      "causal": false,
      "dtype": "torch.float16"
    },
    "best": {
      "BM": 64,
      "BN": 128,
      "avg_ms": 23.2325
    },
    "top3": [
      {
        "BM": 64,
        "BN": 128,
        "avg_ms": 23.2325
      },
      {
        "BM": 64,
        "BN": 32,
        "avg_ms": 91.6851
      },
      {
        "BM": 32,
        "BN": 256,
        "avg_ms": 216.4606
      }
    ],
    "all_tested": [
      {
        "BM": 64,
        "BN": 128,
        "avg_ms": 23.2325
      },
      {
        "BM": 64,
        "BN": 32,
        "avg_ms": 91.6851
      },
      {
        "BM": 32,
        "BN": 256,
        "avg_ms": 216.4606
      },
      {
        "BM": 32,
        "BN": 32,
        "avg_ms": 324.5048
      },
      {
        "BM": 64,
        "BN": 256,
        "avg_ms": 984.0792
      },
      {
        "BM": 64,
        "BN": 64,
        "avg_ms": 1016.7216
      },
      {
        "BM": 32,
        "BN": 128,
        "avg_ms": 2112.418
      },
      {
        "BM": 32,
        "BN": 64,
        "avg_ms": 5970.0017
      }
    ],
    "failed_count": 4
  },
  "case_09": {
    "params": {
      "Z": 128,
      "H": 8,
      "N_CTX": 2048,
      "HEAD_DIM": 128,
      "causal": false,
      "dtype": "torch.float16"
    },
    "best": {
      "BM": 128,
      "BN": 256,
      "avg_ms": 26.1882
    },
    "top3": [
      {
        "BM": 128,
        "BN": 256,
        "avg_ms": 26.1882
      },
      {
        "BM": 64,
        "BN": 256,
        "avg_ms": 46.2817
      },
      {
        "BM": 64,
        "BN": 128,
        "avg_ms": 91.8306
      }
    ],
    "all_tested": [
      {
        "BM": 128,
        "BN": 256,
        "avg_ms": 26.1882
      },
      {
        "BM": 64,
        "BN": 256,
        "avg_ms": 46.2817
      },
      {
        "BM": 64,
        "BN": 128,
        "avg_ms": 91.8306
      },
      {
        "BM": 128,
        "BN": 64,
        "avg_ms": 92.2763
      },
      {
        "BM": 128,
        "BN": 32,
        "avg_ms": 184.3068
      },
      {
        "BM": 64,
        "BN": 32,
        "avg_ms": 364.5072
      },
      {
        "BM": 128,
        "BN": 128,
        "avg_ms": 833.9182
      },
      {
        "BM": 32,
        "BN": 256,
        "avg_ms": 856.219
      },
      {
        "BM": 32,
        "BN": 64,
        "avg_ms": 1031.6523
      },
      {
        "BM": 64,
        "BN": 64,
        "avg_ms": 1116.6446
      },
      {
        "BM": 32,
        "BN": 128,
        "avg_ms": 1879.1948
      },
      {
        "BM": 32,
        "BN": 32,
        "avg_ms": 2212.3488
      }
    ],
    "failed_count": 4
  },
  "case_10": {
    "params": {
      "Z": 128,
      "H": 8,
      "N_CTX": 2048,
      "HEAD_DIM": 256,
      "causal": false,
      "dtype": "torch.float16"
    },
    "best": {
      "BM": 64,
      "BN": 256,
      "avg_ms": 45.9278
    },
    "top3": [
      {
        "BM": 64,
        "BN": 256,
        "avg_ms": 45.9278
      },
      {
        "BM": 64,
        "BN": 128,
        "avg_ms": 92.2787
      },
      {
        "BM": 64,
        "BN": 64,
        "avg_ms": 184.2413
      }
    ],
    "all_tested": [
      {
        "BM": 64,
        "BN": 256,
        "avg_ms": 45.9278
      },
      {
        "BM": 64,
        "BN": 128,
        "avg_ms": 92.2787
      },
      {
        "BM": 64,
        "BN": 64,
        "avg_ms": 184.2413
      },
      {
        "BM": 64,
        "BN": 32,
        "avg_ms": 367.2167
      },
      {
        "BM": 32,
        "BN": 256,
        "avg_ms": 864.0252
      },
      {
        "BM": 32,
        "BN": 128,
        "avg_ms": 923.6851
      },
      {
        "BM": 32,
        "BN": 64,
        "avg_ms": 1038.954
      },
      {
        "BM": 32,
        "BN": 32,
        "avg_ms": 1890.705
      }
    ],
    "failed_count": 4
  },
  "case_11": {
    "params": {
      "Z": 128,
      "H": 8,
      "N_CTX": 4096,
      "HEAD_DIM": 128,
      "causal": false,
      "dtype": "torch.float16"
    },
    "best": {
      "BM": 128,
      "BN": 256,
      "avg_ms": 102.2314
    },
    "top3": [
      {
        "BM": 128,
        "BN": 256,
        "avg_ms": 102.2314
      },
      {
        "BM": 64,
        "BN": 512,
        "avg_ms": 117.1774
      },
      {
        "BM": 64,
        "BN": 256,
        "avg_ms": 183.7771
      }
    ],
    "all_tested": [
      {
        "BM": 128,
        "BN": 256,
        "avg_ms": 102.2314
      },
      {
        "BM": 64,
        "BN": 512,
        "avg_ms": 117.1774
      },
      {
        "BM": 64,
        "BN": 256,
        "avg_ms": 183.7771
      },
      {
        "BM": 128,
        "BN": 128,
        "avg_ms": 184.6196
      },
      {
        "BM": 64,
        "BN": 128,
        "avg_ms": 366.3592
      },
      {
        "BM": 128,
        "BN": 64,
        "avg_ms": 368.5956
      },
      {
        "BM": 64,
        "BN": 64,
        "avg_ms": 733.0233
      },
      {
        "BM": 128,
        "BN": 32,
        "avg_ms": 736.6989
      },
      {
        "BM": 64,
        "BN": 32,
        "avg_ms": 1463.0582
      },
      {
        "BM": 32,
        "BN": 512,
        "avg_ms": 3311.6222
      },
      {
        "BM": 32,
        "BN": 256,
        "avg_ms": 3427.1399
      },
      {
        "BM": 32,
        "BN": 128,
        "avg_ms": 3671.2752
      },
      {
        "BM": 32,
        "BN": 64,
        "avg_ms": 4126.0523
      },
      {
        "BM": 32,
        "BN": 32,
        "avg_ms": 5095.2312
      }
    ],
    "failed_count": 5
  },
  "case_12": {
    "params": {
      "Z": 128,
      "H": 8,
      "N_CTX": 8192,
      "HEAD_DIM": 64,
      "causal": false,
      "dtype": "torch.float16"
    },
    "best": {
      "BM": 128,
      "BN": 512,
      "avg_ms": 302.9548
    },
    "top3": [
      {
        "BM": 128,
        "BN": 512,
        "avg_ms": 302.9548
      },
      {
        "BM": 256,
        "BN": 256,
        "avg_ms": 356.1929
      },
      {
        "BM": 256,
        "BN": 128,
        "avg_ms": 388.5916
      }
    ],
    "all_tested": [
      {
        "BM": 128,
        "BN": 512,
        "avg_ms": 302.9548
      },
      {
        "BM": 256,
        "BN": 256,
        "avg_ms": 356.1929
      },
      {
        "BM": 256,
        "BN": 128,
        "avg_ms": 388.5916
      },
      {
        "BM": 128,
        "BN": 256,
        "avg_ms": 395.3008
      },
      {
        "BM": 64,
        "BN": 512,
        "avg_ms": 425.3722
      },
      {
        "BM": 64,
        "BN": 256,
        "avg_ms": 733.9504
      },
      {
        "BM": 128,
        "BN": 128,
        "avg_ms": 734.3501
      },
      {
        "BM": 256,
        "BN": 64,
        "avg_ms": 740.4967
      },
      {
        "BM": 64,
        "BN": 128,
        "avg_ms": 1465.3153
      },
      {
        "BM": 128,
        "BN": 64,
        "avg_ms": 1466.7606
      },
      {
        "BM": 256,
        "BN": 32,
        "avg_ms": 1475.2397
      },
      {
        "BM": 64,
        "BN": 64,
        "avg_ms": 2932.9633
      },
      {
        "BM": 128,
        "BN": 32,
        "avg_ms": 2938.1539
      },
      {
        "BM": 64,
        "BN": 32,
        "avg_ms": 5846.9903
      },
      {
        "BM": 32,
        "BN": 512,
        "avg_ms": 13195.3276
      },
      {
        "BM": 32,
        "BN": 256,
        "avg_ms": 13666.3528
      },
      {
        "BM": 32,
        "BN": 128,
        "avg_ms": 14591.087
      },
      {
        "BM": 32,
        "BN": 64,
        "avg_ms": 16363.8704
      },
      {
        "BM": 32,
        "BN": 32,
        "avg_ms": 20427.4864
      }
    ],
    "failed_count": 0
  }
}